openreview/__init__.py
openreview/duplicate_domains.json
openreview/openreview.py
openreview/tools.py
openreview/agora/__init__.py
openreview/agora/agora.py
openreview/agora/process/article_process.py
openreview/agora/process/assign_editor_process.py
openreview/agora/process/assign_reviewer_process.py
openreview/agora/process/comment_process.py
openreview/agora/process/meta_review_process.py
openreview/agora/process/moderate_process.py
openreview/agora/process/review_process.py
openreview/agora/process/revision_process.py
openreview/agora/process/submission_process.py
openreview/agora/process/suggest_reviewer_process.py
openreview/agora/webfield/homepage.js
openreview/api/__init__.py
openreview/api/client.py
openreview/api/iThenticate_client.py
openreview/arr/__init__.py
openreview/arr/arr.py
openreview/arr/helpers.py
openreview/arr/invitation.py
openreview/arr/management/setup_ae_matching.py
openreview/arr/management/setup_authors_to_reviewers.py
openreview/arr/management/setup_metareview_release.py
openreview/arr/management/setup_proposed_assignments.py
openreview/arr/management/setup_rebuttal_end.py
openreview/arr/management/setup_rebuttal_start.py
openreview/arr/management/setup_review_release.py
openreview/arr/management/setup_reviewer_matching.py
openreview/arr/management/setup_sae_ae_assignments.py
openreview/arr/management/setup_sae_matching.py
openreview/arr/management/setup_shared_data.py
openreview/arr/process/checklist_preprocess.py
openreview/arr/process/checklist_process.py
openreview/arr/process/comment_process.py
openreview/arr/process/configuration_process.py
openreview/arr/process/emergency_load_preprocess.py
openreview/arr/process/emergency_load_process.py
openreview/arr/process/max_load_preprocess.py
openreview/arr/process/max_load_process.py
openreview/arr/process/metareview_process.py
openreview/arr/process/preprint_release_submission_process.py
openreview/arr/process/review_preprocess.py
openreview/arr/process/review_process.py
openreview_py-1.54.7.dist-info/licenses/LICENSE
openreview_py-1.54.7.dist-info/METADATA
openreview_py-1.54.7.dist-info/WHEEL
openreview_py-1.54.7.dist-info/top_level.txt
openreview_py-1.54.7.dist-info/RECORD
