Metadata-Version: 2.4
Name: openreview-py
Version: 1.54.7
Summary: OpenReview API Python client library
Author-email: OpenReview Team <info@openreview.net>
License: MIT
Project-URL: Homepage, https://github.com/openreview/openreview-py
Requires-Python: >=3.8
License-File: LICENSE
Requires-Dist: pycryptodome
Requires-Dist: requests>=2.18.4
Requires-Dist: future
Requires-Dist: tqdm
Requires-Dist: Deprecated
Requires-Dist: pylatexenc
Requires-Dist: tld>=0.12
Requires-Dist: pyjwt
Requires-Dist: numpy
Requires-Dist: litellm==1.76.1
Provides-Extra: docs
Requires-Dist: nbsphinx; extra == "docs"
Requires-Dist: sphinx; extra == "docs"
Requires-Dist: sphinx_rtd_theme; extra == "docs"
Requires-Dist: nbformat; extra == "docs"
Dynamic: license-file
